{
  "currentStep": "publish github pages",
  "heartbeatAt": "2026-07-09T16:01:32.677199+00:00",
  "maxPostAgeDays": 30,
  "message": "",
  "pid": 97375,
  "startedAt": "2026-07-09T16:00:05.041705+00:00",
  "status": "running",
  "steps": [
    {
      "command": [
        "/Library/Developer/CommandLineTools/usr/bin/python3",
        "scripts/build_social_sources.py"
      ],
      "finishedAt": "2026-07-09T16:00:05.077142+00:00",
      "name": "build social sources",
      "returnCode": 0,
      "startedAt": "2026-07-09T16:00:05.043524+00:00",
      "status": "ok"
    },
    {
      "command": [
        "/Library/Developer/CommandLineTools/usr/bin/python3",
        "scripts/rsshub_fetcher.py"
      ],
      "finishedAt": "2026-07-09T16:01:19.661430+00:00",
      "name": "fetch rsshub",
      "returnCode": 0,
      "startedAt": "2026-07-09T16:00:05.077467+00:00",
      "status": "ok"
    },
    {
      "command": [
        "/Library/Developer/CommandLineTools/usr/bin/python3",
        "scripts/youtube_ytdlp_fetcher.py"
      ],
      "finishedAt": "2026-07-09T16:01:31.740891+00:00",
      "name": "fetch youtube",
      "returnCode": 0,
      "startedAt": "2026-07-09T16:01:19.662577+00:00",
      "status": "ok"
    },
    {
      "command": [
        "/Library/Developer/CommandLineTools/usr/bin/python3",
        "scripts/apify_facebook_fetcher.py"
      ],
      "finishedAt": "2026-07-09T16:01:31.777973+00:00",
      "name": "fetch facebook apify",
      "returnCode": 0,
      "startedAt": "2026-07-09T16:01:31.741313+00:00",
      "status": "ok"
    },
    {
      "command": [
        "/Library/Developer/CommandLineTools/usr/bin/python3",
        "scripts/official_site_fetcher.py"
      ],
      "finishedAt": "2026-07-09T16:01:31.805875+00:00",
      "name": "fetch official sites",
      "returnCode": 0,
      "startedAt": "2026-07-09T16:01:31.778333+00:00",
      "status": "ok"
    },
    {
      "command": [
        "/Library/Developer/CommandLineTools/usr/bin/python3",
        "scripts/social_feed_watchdog.py",
        "--max-post-age-days",
        "30"
      ],
      "finishedAt": "2026-07-09T16:01:31.841525+00:00",
      "name": "watch social feeds",
      "returnCode": 0,
      "startedAt": "2026-07-09T16:01:31.806247+00:00",
      "status": "ok"
    },
    {
      "command": [
        "/Library/Developer/CommandLineTools/usr/bin/python3",
        "scripts/fetch_media_cache.py"
      ],
      "finishedAt": "2026-07-09T16:01:32.330349+00:00",
      "name": "cache media",
      "returnCode": 0,
      "startedAt": "2026-07-09T16:01:31.841877+00:00",
      "status": "ok"
    },
    {
      "command": [
        "/Library/Developer/CommandLineTools/usr/bin/python3",
        "scripts/build_public_data.py"
      ],
      "finishedAt": "2026-07-09T16:01:32.379685+00:00",
      "name": "build public data",
      "returnCode": 0,
      "startedAt": "2026-07-09T16:01:32.330884+00:00",
      "status": "ok"
    },
    {
      "command": [
        "/Library/Developer/CommandLineTools/usr/bin/python3",
        "scripts/build_spectrum.py"
      ],
      "finishedAt": "2026-07-09T16:01:32.415308+00:00",
      "name": "build spectrum",
      "returnCode": 0,
      "startedAt": "2026-07-09T16:01:32.380039+00:00",
      "status": "ok"
    },
    {
      "command": [
        "/Library/Developer/CommandLineTools/usr/bin/python3",
        "scripts/generate_rss_feeds.py"
      ],
      "finishedAt": "2026-07-09T16:01:32.472505+00:00",
      "name": "generate rss feeds",
      "returnCode": 0,
      "startedAt": "2026-07-09T16:01:32.415683+00:00",
      "status": "ok"
    },
    {
      "command": [
        "/Library/Developer/CommandLineTools/usr/bin/python3",
        "scripts/build_status_page.py"
      ],
      "finishedAt": "2026-07-09T16:01:32.573398+00:00",
      "name": "build status page",
      "returnCode": 0,
      "startedAt": "2026-07-09T16:01:32.472938+00:00",
      "status": "ok"
    },
    {
      "command": [
        "/Library/Developer/CommandLineTools/usr/bin/python3",
        "scripts/generate_site_pages.py"
      ],
      "finishedAt": "2026-07-09T16:01:32.601143+00:00",
      "name": "generate site pages",
      "returnCode": 0,
      "startedAt": "2026-07-09T16:01:32.573776+00:00",
      "status": "ok"
    },
    {
      "command": [
        "/Library/Developer/CommandLineTools/usr/bin/python3",
        "scripts/generate_seo_pages.py"
      ],
      "finishedAt": "2026-07-09T16:01:32.621742+00:00",
      "name": "generate SEO pages",
      "returnCode": 0,
      "startedAt": "2026-07-09T16:01:32.601554+00:00",
      "status": "ok"
    },
    {
      "command": [
        "/Library/Developer/CommandLineTools/usr/bin/python3",
        "scripts/check_source_coverage.py"
      ],
      "finishedAt": "2026-07-09T16:01:32.642120+00:00",
      "name": "check source coverage",
      "returnCode": 0,
      "startedAt": "2026-07-09T16:01:32.622116+00:00",
      "status": "ok"
    },
    {
      "command": [
        "/Library/Developer/CommandLineTools/usr/bin/python3",
        "scripts/validate_public_outputs.py"
      ],
      "finishedAt": "2026-07-09T16:01:32.676550+00:00",
      "name": "validate public outputs",
      "returnCode": 0,
      "startedAt": "2026-07-09T16:01:32.642527+00:00",
      "status": "ok"
    },
    {
      "command": [
        "/Library/Developer/CommandLineTools/usr/bin/python3",
        "scripts/publish_github_pages.py"
      ],
      "finishedAt": "",
      "name": "publish github pages",
      "returnCode": null,
      "startedAt": "2026-07-09T16:01:32.677196+00:00",
      "status": "running"
    }
  ],
  "version": 1
}
