{
  "candidates": [
    {
      "candidateId": "chang-ching",
      "dominantTopic": "競選",
      "postCount": 26,
      "topicProportions": {
        "住宅": 0.0313,
        "兩岸外交": 0.2104,
        "教育": 0.0453,
        "文化觀光": 0.0515,
        "治安": 0.0403,
        "競選": 0.3246,
        "經濟": 0.0795,
        "議會監督": 0.1634,
        "防災": 0.0537
      }
    },
    {
      "candidateId": "chang-san-cheng",
      "dominantTopic": "防災",
      "postCount": 45,
      "topicProportions": {
        "交通": 0.0793,
        "教育": 0.1043,
        "文化觀光": 0.1879,
        "治安": 0.0334,
        "環境": 0.0555,
        "社福": 0.0194,
        "競選": 0.0462,
        "經濟": 0.1215,
        "醫療": 0.0647,
        "防災": 0.1901,
        "體育": 0.0977
      }
    },
    {
      "candidateId": "chen-ting-fei",
      "dominantTopic": "防災",
      "postCount": 95,
      "topicProportions": {
        "交通": 0.0952,
        "住宅": 0.0142,
        "兩岸外交": 0.034,
        "教育": 0.0021,
        "文化觀光": 0.1583,
        "環境": 0.0654,
        "社福": 0.061,
        "競選": 0.0464,
        "經濟": 0.124,
        "議會監督": 0.0256,
        "醫療": 0.0104,
        "防災": 0.3326,
        "體育": 0.0308
      }
    },
    {
      "candidateId": "chiang-chi-chen",
      "dominantTopic": "經濟",
      "postCount": 71,
      "topicProportions": {
        "交通": 0.0651,
        "住宅": 0.0154,
        "兩岸外交": 0.0511,
        "教育": 0.0769,
        "文化觀光": 0.0732,
        "治安": 0.0061,
        "環境": 0.0226,
        "社福": 0.0402,
        "競選": 0.0712,
        "經濟": 0.2884,
        "議會監督": 0.048,
        "醫療": 0.0482,
        "防災": 0.0818,
        "體育": 0.1118
      }
    },
    {
      "candidateId": "chiang-wanan",
      "dominantTopic": "防災",
      "postCount": 49,
      "topicProportions": {
        "交通": 0.1249,
        "住宅": 0.0783,
        "兩岸外交": 0.0709,
        "教育": 0.062,
        "文化觀光": 0.1278,
        "治安": 0.0045,
        "環境": 0.0353,
        "社福": 0.0279,
        "經濟": 0.0985,
        "議會監督": 0.097,
        "醫療": 0.0694,
        "防災": 0.1708,
        "體育": 0.0327
      }
    },
    {
      "candidateId": "ho-hsin-chun",
      "dominantTopic": "競選",
      "postCount": 96,
      "topicProportions": {
        "交通": 0.1045,
        "住宅": 0.0117,
        "兩岸外交": 0.0075,
        "教育": 0.125,
        "文化觀光": 0.0618,
        "治安": 0.0208,
        "環境": 0.0882,
        "社福": 0.0763,
        "競選": 0.1437,
        "經濟": 0.1275,
        "議會監督": 0.0143,
        "醫療": 0.0573,
        "防災": 0.1216,
        "體育": 0.0397
      }
    },
    {
      "candidateId": "hsieh-lung-chieh",
      "dominantTopic": "議會監督",
      "postCount": 95,
      "topicProportions": {
        "交通": 0.058,
        "住宅": 0.0081,
        "兩岸外交": 0.0722,
        "教育": 0.0499,
        "文化觀光": 0.0151,
        "治安": 0.1324,
        "環境": 0.0222,
        "社福": 0.0492,
        "競選": 0.13,
        "經濟": 0.1146,
        "議會監督": 0.1377,
        "醫療": 0.1331,
        "防災": 0.0774
      }
    },
    {
      "candidateId": "huang-shih-chieh",
      "dominantTopic": "競選",
      "postCount": 85,
      "topicProportions": {
        "交通": 0.0882,
        "住宅": 0.0052,
        "教育": 0.0775,
        "文化觀光": 0.1541,
        "治安": 0.0132,
        "環境": 0.0231,
        "社福": 0.0453,
        "競選": 0.2078,
        "經濟": 0.0894,
        "議會監督": 0.0078,
        "醫療": 0.0447,
        "防災": 0.1983,
        "體育": 0.0455
      }
    },
    {
      "candidateId": "ko-chih-en",
      "dominantTopic": "競選",
      "postCount": 82,
      "topicProportions": {
        "交通": 0.0484,
        "住宅": 0.0184,
        "教育": 0.1167,
        "文化觀光": 0.1262,
        "治安": 0.0299,
        "環境": 0.0305,
        "社福": 0.0951,
        "競選": 0.1676,
        "經濟": 0.1431,
        "議會監督": 0.0625,
        "醫療": 0.0276,
        "防災": 0.111,
        "體育": 0.0231
      }
    },
    {
      "candidateId": "lai-jui-lung",
      "dominantTopic": "防災",
      "postCount": 110,
      "topicProportions": {
        "交通": 0.0438,
        "住宅": 0.0253,
        "兩岸外交": 0.0263,
        "教育": 0.0634,
        "文化觀光": 0.1156,
        "治安": 0.0117,
        "環境": 0.0643,
        "社福": 0.0463,
        "競選": 0.1041,
        "經濟": 0.1576,
        "議會監督": 0.0386,
        "醫療": 0.0379,
        "防災": 0.1877,
        "體育": 0.0773
      }
    },
    {
      "candidateId": "lee-shih-chuan",
      "dominantTopic": "醫療",
      "postCount": 57,
      "topicProportions": {
        "交通": 0.1527,
        "住宅": 0.0192,
        "教育": 0.0809,
        "文化觀光": 0.1634,
        "環境": 0.0219,
        "社福": 0.1443,
        "競選": 0.072,
        "經濟": 0.1027,
        "議會監督": 0.0028,
        "醫療": 0.1657,
        "防災": 0.0401,
        "體育": 0.0343
      }
    },
    {
      "candidateId": "lin-yi-feng",
      "dominantTopic": "文化觀光",
      "postCount": 6,
      "topicProportions": {
        "文化觀光": 0.5795,
        "競選": 0.4205
      }
    },
    {
      "candidateId": "shen-poyang",
      "dominantTopic": "競選",
      "postCount": 84,
      "topicProportions": {
        "交通": 0.0541,
        "住宅": 0.0083,
        "兩岸外交": 0.1105,
        "教育": 0.1131,
        "文化觀光": 0.1512,
        "治安": 0.0282,
        "環境": 0.0326,
        "社福": 0.0564,
        "競選": 0.1592,
        "經濟": 0.0282,
        "議會監督": 0.0458,
        "醫療": 0.0181,
        "防災": 0.0808,
        "體育": 0.1136
      }
    },
    {
      "candidateId": "su-chiaohui",
      "dominantTopic": "文化觀光",
      "postCount": 91,
      "topicProportions": {
        "交通": 0.1349,
        "住宅": 0.0696,
        "兩岸外交": 0.0078,
        "教育": 0.0983,
        "文化觀光": 0.1939,
        "環境": 0.0294,
        "社福": 0.1074,
        "競選": 0.1429,
        "經濟": 0.0383,
        "議會監督": 0.0129,
        "醫療": 0.0948,
        "防災": 0.0622,
        "體育": 0.0077
      }
    }
  ],
  "count": 14,
  "version": 1
}
