{
  "candidates": [
    {
      "candidateId": "chang-ching",
      "dominantTopic": "競選",
      "postCount": 28,
      "topicProportions": {
        "住宅": 0.028,
        "兩岸外交": 0.1879,
        "教育": 0.0405,
        "文化觀光": 0.046,
        "治安": 0.065,
        "競選": 0.2899,
        "經濟": 0.1049,
        "議會監督": 0.1899,
        "防災": 0.048
      }
    },
    {
      "candidateId": "chang-san-cheng",
      "dominantTopic": "文化觀光",
      "postCount": 47,
      "topicProportions": {
        "交通": 0.077,
        "教育": 0.1013,
        "文化觀光": 0.2112,
        "治安": 0.0324,
        "環境": 0.0539,
        "社福": 0.0188,
        "競選": 0.0449,
        "經濟": 0.118,
        "醫療": 0.0628,
        "防災": 0.1847,
        "體育": 0.0949
      }
    },
    {
      "candidateId": "chen-ting-fei",
      "dominantTopic": "防災",
      "postCount": 99,
      "topicProportions": {
        "交通": 0.092,
        "住宅": 0.0137,
        "兩岸外交": 0.0329,
        "教育": 0.002,
        "文化觀光": 0.1601,
        "環境": 0.0631,
        "社福": 0.0589,
        "競選": 0.0448,
        "經濟": 0.1271,
        "議會監督": 0.0247,
        "醫療": 0.0298,
        "防災": 0.3211,
        "體育": 0.0297
      }
    },
    {
      "candidateId": "chiang-chi-chen",
      "dominantTopic": "經濟",
      "postCount": 76,
      "topicProportions": {
        "交通": 0.0654,
        "住宅": 0.0183,
        "兩岸外交": 0.0538,
        "教育": 0.1005,
        "文化觀光": 0.0685,
        "治安": 0.0057,
        "環境": 0.0212,
        "社福": 0.0376,
        "競選": 0.0666,
        "經濟": 0.2696,
        "議會監督": 0.0499,
        "醫療": 0.0451,
        "防災": 0.0765,
        "體育": 0.1215
      }
    },
    {
      "candidateId": "chiang-wanan",
      "dominantTopic": "防災",
      "postCount": 49,
      "topicProportions": {
        "交通": 0.1249,
        "住宅": 0.0783,
        "兩岸外交": 0.0709,
        "教育": 0.062,
        "文化觀光": 0.1278,
        "治安": 0.0045,
        "環境": 0.0353,
        "社福": 0.0279,
        "經濟": 0.0985,
        "議會監督": 0.097,
        "醫療": 0.0694,
        "防災": 0.1708,
        "體育": 0.0327
      }
    },
    {
      "candidateId": "ho-hsin-chun",
      "dominantTopic": "競選",
      "postCount": 102,
      "topicProportions": {
        "交通": 0.0978,
        "住宅": 0.011,
        "兩岸外交": 0.0195,
        "教育": 0.117,
        "文化觀光": 0.0578,
        "治安": 0.0195,
        "環境": 0.0906,
        "社福": 0.0822,
        "競選": 0.1503,
        "經濟": 0.1363,
        "議會監督": 0.0133,
        "醫療": 0.0536,
        "防災": 0.1138,
        "體育": 0.0372
      }
    },
    {
      "candidateId": "hsieh-lung-chieh",
      "dominantTopic": "競選",
      "postCount": 98,
      "topicProportions": {
        "交通": 0.0574,
        "住宅": 0.008,
        "兩岸外交": 0.0714,
        "教育": 0.0493,
        "文化觀光": 0.0149,
        "治安": 0.1346,
        "環境": 0.022,
        "社福": 0.0663,
        "競選": 0.1358,
        "經濟": 0.1177,
        "議會監督": 0.1222,
        "醫療": 0.1239,
        "防災": 0.0766
      }
    },
    {
      "candidateId": "huang-shih-chieh",
      "dominantTopic": "競選",
      "postCount": 91,
      "topicProportions": {
        "交通": 0.1046,
        "住宅": 0.0151,
        "教育": 0.0856,
        "文化觀光": 0.1464,
        "治安": 0.0114,
        "環境": 0.0257,
        "社福": 0.0544,
        "競選": 0.1961,
        "經濟": 0.1048,
        "議會監督": 0.0067,
        "醫療": 0.0386,
        "防災": 0.1713,
        "體育": 0.0393
      }
    },
    {
      "candidateId": "ko-chih-en",
      "dominantTopic": "競選",
      "postCount": 93,
      "topicProportions": {
        "交通": 0.0466,
        "住宅": 0.0158,
        "教育": 0.1134,
        "文化觀光": 0.1224,
        "治安": 0.0257,
        "環境": 0.0438,
        "社福": 0.0922,
        "競選": 0.2038,
        "經濟": 0.1327,
        "議會監督": 0.0587,
        "醫療": 0.0237,
        "防災": 0.0953,
        "體育": 0.026
      }
    },
    {
      "candidateId": "lai-jui-lung",
      "dominantTopic": "防災",
      "postCount": 117,
      "topicProportions": {
        "交通": 0.0423,
        "住宅": 0.0244,
        "兩岸外交": 0.0254,
        "教育": 0.0612,
        "文化觀光": 0.1382,
        "治安": 0.0113,
        "環境": 0.062,
        "社福": 0.0447,
        "競選": 0.1004,
        "經濟": 0.1605,
        "議會監督": 0.0373,
        "醫療": 0.0366,
        "防災": 0.1812,
        "體育": 0.0746
      }
    },
    {
      "candidateId": "lee-shih-chuan",
      "dominantTopic": "醫療",
      "postCount": 60,
      "topicProportions": {
        "交通": 0.1451,
        "住宅": 0.0182,
        "教育": 0.0769,
        "文化觀光": 0.1552,
        "環境": 0.0208,
        "社福": 0.1486,
        "競選": 0.0813,
        "經濟": 0.0976,
        "議會監督": 0.0026,
        "醫療": 0.1831,
        "防災": 0.0381,
        "體育": 0.0326
      }
    },
    {
      "candidateId": "lin-yi-feng",
      "dominantTopic": "文化觀光",
      "postCount": 6,
      "topicProportions": {
        "文化觀光": 0.5795,
        "競選": 0.4205
      }
    },
    {
      "candidateId": "shen-poyang",
      "dominantTopic": "文化觀光",
      "postCount": 93,
      "topicProportions": {
        "交通": 0.0543,
        "住宅": 0.0191,
        "兩岸外交": 0.0992,
        "教育": 0.1073,
        "文化觀光": 0.1669,
        "治安": 0.0253,
        "環境": 0.0293,
        "社福": 0.0507,
        "競選": 0.1509,
        "經濟": 0.0316,
        "議會監督": 0.0411,
        "醫療": 0.0162,
        "防災": 0.0725,
        "體育": 0.1355
      }
    },
    {
      "candidateId": "su-chiaohui",
      "dominantTopic": "文化觀光",
      "postCount": 97,
      "topicProportions": {
        "交通": 0.1348,
        "住宅": 0.069,
        "兩岸外交": 0.0072,
        "教育": 0.0958,
        "文化觀光": 0.1913,
        "環境": 0.0375,
        "社福": 0.1061,
        "競選": 0.1531,
        "經濟": 0.0353,
        "議會監督": 0.0119,
        "醫療": 0.0938,
        "防災": 0.0573,
        "體育": 0.0071
      }
    }
  ],
  "count": 14,
  "version": 1
}
